alphabet.py
main.py
modules.py
runs/config.ini
runs/nato_phonetics.py
wpatpy_yehor-1.0.1.dist-info/METADATA
wpatpy_yehor-1.0.1.dist-info/WHEEL
wpatpy_yehor-1.0.1.dist-info/entry_points.txt
wpatpy_yehor-1.0.1.dist-info/top_level.txt
wpatpy_yehor-1.0.1.dist-info/RECORD
