Metadata-Version: 2.4
Name: WPATpy_yehor
Version: 1.0.1
Summary: Translate weird phonetic alphabets to sentences and vice versa
Author: yehor0
Project-URL: Homepage, https://github.com/yehorscode/WPATpy
Project-URL: Issues, https://github.com/yehorscode/WPATpy/issues
Classifier: Programming Language :: Python :: 3
Classifier: Operating System :: OS Independent
Requires-Python: >=3.9
Requires-Dist: colorama==0.4.6
Requires-Dist: mdurl==0.1.2
Requires-Dist: Pygments==2.19.2
Requires-Dist: pyttsx3==2.99
Requires-Dist: rich==14.2.0
Requires-Dist: typing_extensions==4.15.0
